mutwo/isis_converters/__init__.py
mutwo/isis_converters/configurations.py
mutwo/isis_converters/isis.py
mutwo/isis_converters/constants/XSAMPA.py
mutwo/isis_converters/constants/__init__.py
mutwo/isis_utilities/__init__.py
mutwo/isis_utilities/exceptions.py
mutwo/isis_version/__init__.py
mutwo.isis-0.8.2.dist-info/LICENSE
mutwo.isis-0.8.2.dist-info/METADATA
mutwo.isis-0.8.2.dist-info/WHEEL
mutwo.isis-0.8.2.dist-info/top_level.txt
mutwo.isis-0.8.2.dist-info/RECORD
