Metadata-Version: 2.1
Name: mutwo.isis
Version: 0.8.2
Summary: ISiS extension for event based framework for generative art
Home-page: https://github.com/mutwo-org/mutwo.isis
Author: Levin Eric Zimmermann
Author-email: levin.eric.zimmermann@posteo.eu
License: GPL
Project-URL: Documentation, https://mutwo.readthedocs.io/en/latest/
Requires-Python: >=3.9, <4
License-File: LICENSE
Requires-Dist: mutwo.core (<1.0.0,>=0.61.4)
Requires-Dist: mutwo.music (<1.0.0,>=0.17.0)
Provides-Extra: testing
Requires-Dist: nose ; extra == 'testing'
Requires-Dist: coveralls ; extra == 'testing'
